{
	"name": "ds_4_file_list_json",
	"properties": {
		"linkedServiceName": {
			"referenceName": "ls_ablob_src",
			"type": "LinkedServiceReference"
		},
		"annotations": [],
		"type": "Json",
		"typeProperties": {
			"location": {
				"type": "AzureBlobStorageLocation",
				"fileName": "ecdc-file-list.json",
				"container": "configs"
			}
		},
		"schema": {
			"type": "object",
			"properties": {
				"sourceBaseURL": {
					"type": "string"
				},
				"sourceRelativeURL": {
					"type": "string"
				},
				"sinkFileName": {
					"type": "string"
				}
			}
		}
	},
	"type": "Microsoft.DataFactory/factories/datasets"
}